s3stasher/__init__.py
s3stasher/s3stasher.py
s3stasher-0.0.5.dist-info/LICENSE
s3stasher-0.0.5.dist-info/METADATA
s3stasher-0.0.5.dist-info/WHEEL
s3stasher-0.0.5.dist-info/RECORD
