Metadata-Version: 2.1
Name: s3stasher
Version: 0.0.5
Summary: A python package for working with objects in AWS S3 as if they were local files, including cache management and offline usage.
Home-page: https://github.com/bsiranosian/s3stasher
License: MIT
Author: Ben Siranosian
Author-email: bsiranosian@gmail.com
Requires-Python: >=3.10,<4.0
Classifier: License :: OSI Approved :: MIT License
Classifier: Programming Language :: Python :: 3
Classifier: Programming Language :: Python :: 3.10
Classifier: Programming Language :: Python :: 3.11
Classifier: Programming Language :: Python :: 3.12
Requires-Dist: boto3 (>=1.36.21,<2.0.0)
Requires-Dist: gitpython (>=3.1.44,<4.0.0)
Requires-Dist: pytest (>=8.3.4,<9.0.0)
Requires-Dist: pytest-cov (>=6.0.0,<7.0.0)
Requires-Dist: python-dotenv (>=1.0.1,<2.0.0)
Requires-Dist: pytz (>=2025.1,<2026.0)
Requires-Dist: tqdm (>=4.67.1,<5.0.0)
Requires-Dist: tzlocal (>=5.3,<6.0)
Project-URL: Repository, https://github.com/bsiranosian/s3stasher
